{
  "schemaVersion": "2.0",
  "version": "1.9.1",
  "packages": {
    "amazon": {
      "_any": {
        "x86_64": {
          "file": "amazon-guardduty-agent-1.9.1.x86_64.rpm.zip"
        },
        "arm64": {
          "file": "amazon-guardduty-agent-1.9.1.arm64.rpm.zip"
        }
      }
    },
    "debian": {
      "_any": {
        "x86_64": {
          "file": "amazon-guardduty-agent-1.9.1.amd64.deb.zip"
        },
        "arm64": {
          "file": "amazon-guardduty-agent-1.9.1.arm64.deb.zip"
        }
      }
    },
    "ubuntu": {
      "_any": {
        "x86_64": {
          "file": "amazon-guardduty-agent-1.9.1.amd64.deb.zip"
        },
        "arm64": {
          "file": "amazon-guardduty-agent-1.9.1.arm64.deb.zip"
        }
      }
    },
    "redhat": {
      "_any": {
        "x86_64": {
          "file": "amazon-guardduty-agent-1.9.1.x86_64.rpm.zip"
        },
        "arm64": {
          "file": "amazon-guardduty-agent-1.9.1.arm64.rpm.zip"
        }
      }
    },
    "centos": {
      "_any": {
        "x86_64": {
          "file": "amazon-guardduty-agent-1.9.1.x86_64.rpm.zip"
        },
        "arm64": {
          "file": "amazon-guardduty-agent-1.9.1.arm64.rpm.zip"
        }
      }
    },
    "rocky": {
      "_any": {
        "x86_64": {
          "file": "amazon-guardduty-agent-1.9.1.x86_64.rpm.zip"
        },
        "arm64": {
          "file": "amazon-guardduty-agent-1.9.1.arm64.rpm.zip"
        }
      }
    },
    "oracle": {
      "_any": {
        "x86_64": {
          "file": "amazon-guardduty-agent-1.9.1.x86_64.rpm.zip"
        },
        "arm64": {
          "file": "amazon-guardduty-agent-1.9.1.arm64.rpm.zip"
        }
      }
    },
    "fedora": {
      "_any": {
        "x86_64": {
          "file": "amazon-guardduty-agent-1.9.1.x86_64.rpm.zip"
        },
        "arm64": {
          "file": "amazon-guardduty-agent-1.9.1.arm64.rpm.zip"
        }
      }
    }
  },
  "files": {
    "amazon-guardduty-agent-1.9.1.x86_64.rpm.zip": {
      "checksums": {
        "sha256": "2dad5b612371c74d40a9f33a99f5ac97bd6e4fb4900babb9754270959ba91cfe"
      }
    },
    "amazon-guardduty-agent-1.9.1.arm64.rpm.zip": {
      "checksums": {
        "sha256": "7dcf5af08461602c997c128524e14f6c00390359514d3a51e38a3857e61aa5ea"
      }
    },
    "amazon-guardduty-agent-1.9.1.amd64.deb.zip": {
      "checksums": {
        "sha256": "ae37fdffef39625792b116bbc1f82fb87f9e43d72397ec55c9d21d1383b9ac12"
      }
    },
    "amazon-guardduty-agent-1.9.1.arm64.deb.zip": {
      "checksums": {
        "sha256": "8c2dea9aa01d3259a09897e89705db4a0bc9d7b87234437635e4289b923e4102"
      }
    }
  }
}
