{
  "schemaVersion": "2.0",
  "version": "0.21.1",
  "packages": {
    "windows": {
      "_any": {
        "x86_64": {
          "file": "windows-amd64-msi.zip"
        }
      }
    },
    "amazon": {
      "_any": {
        "x86_64": {
          "file": "linux-amd64-rpm.zip"
        },
        "arm64": {
          "file": "linux-arm64-rpm.zip"
        }
      }
    },
    "ubuntu": {
      "_any": {
        "x86_64": {
          "file": "linux-amd64-deb.zip"
        },
        "arm64": {
          "file": "linux-arm64-deb.zip"
        }
      }
    },
    "debian": {
      "_any": {
        "x86_64": {
          "file": "linux-amd64-deb.zip"
        }
      }
    },
    "redhat": {
      "_any": {
        "x86_64": {
          "file": "linux-amd64-rpm.zip"
        },
        "arm64": {
          "file": "linux-arm64-rpm.zip"
        }
      }
    },
    "centos": {
      "_any": {
        "x86_64": {
          "file": "linux-amd64-rpm.zip"
        }
      }
    },
    "suse": {
      "_any": {
        "x86_64": {
          "file": "linux-amd64-rpm.zip"
        },
        "arm64": {
          "file": "linux-arm64-rpm.zip"
        }
      }
    }
  },
  "files": {
    "linux-amd64-rpm.zip": {
      "checksums": {
        "sha256": "0e0910c9390b1074408b5531805a481c4cedc9b7fe61ecef61b36c63a2d78f37"
      }
    },
    "linux-arm64-rpm.zip": {
      "checksums": {
        "sha256": "488677902c11454c9c557e45e5f5671731f9080897503b89f5a6717df3abf8c1"
      }
    },
    "linux-amd64-deb.zip": {
      "checksums": {
        "sha256": "888d781face6b88850a980c3a0382e87542b0655a298d338a80b19243dbf6919"
      }
    },
    "linux-arm64-deb.zip": {
      "checksums": {
        "sha256": "94b26a5f740f609a4a8838749f3165761654efd8505ba61ec76988416c3865dc"
      }
    },
    "windows-amd64-msi.zip": {
      "checksums": {
        "sha256": "6905a19d31cf6817192f3189ce67ca076197f5fe88992d5694e28648eda2cf3e"
      }
    }
  }
}
