{
  "schemaVersion": "2.0",
  "name": "AWSNVMe",
  "version": "1.4.2",
  "packageArn": "arn:aws:ssm:::package/AWSNVMe",
  "publisher": "Amazon AWS",
  "url": "https://amazonaws.com",
  "packages": {
    "windows": {
      "_any": {
        "x86_64": {
          "file": "AWSNVMe-1.4.2.zip"
        }
      }
    }
  },
  "files": {
    "AWSNVMe-1.4.2.zip": {
      "checksums": {
        "sha256": "d219306ebf946c3c6634b1af3001b6adae717fcf253c3b223131b639b377dbcb"
      },
      "downloadLocation": "https://us-east-1-birdwatcher-prod.s3.us-east-1.amazonaws.com/316874961013/AWSNVMe-1.4.2.zip"
    }
  }
}
