{
  "schemaVersion": "2.0",
  "version": "0.5.5",
  "packages": {
    "redhat": {
      "_any": {
        "x86_64": {
          "file": "sapHostExporterPackage_AMAZON.zip"
        }
      }
    },
    "suse": {
      "_any": {
        "x86_64": {
          "file": "sapHostExporterPackage_AMAZON.zip"
        }
      }
    },
    "oracle": {
      "_any": {
        "x86_64": {
          "file": "sapHostExporterPackage_AMAZON.zip"
        }
      }
    }
  },
  "files": {
    "sapHostExporterPackage_AMAZON.zip": {
      "checksums": {
        "sha256": "9ba06b611fed30c00977122adc28dc7f6ec4fc3e07a5c9e2c2c0dce16d4195c5"
      }
    }
  }
}
